{
  "main": {
    "id": "3a2f89ef75937c70",
    "type": "split",
    "children": [
      {
        "id": "e130750272e92f00",
        "type": "tabs",
        "children": [
          {
            "id": "18be168494dfe55f",
            "type": "leaf",
            "state": {
              "type": "canvas",
              "state": {
                "file": "Canvas/Vtable_C.canvas",
                "viewState": {
                  "x": 214.64635161638265,
                  "y": 45.25723810315138,
                  "zoom": 0
                }
              },
              "icon": "lucide-layout-dashboard",
              "title": "Vtable_C"
            }
          },
          {
            "id": "55cac300ec88df2d",
            "type": "leaf",
            "state": {
              "type": "markdown",
              "state": {
                "file": "Ereditarietà.md",
                "mode": "source",
                "backlinks": true,
                "source": false
              },
              "icon": "lucide-file",
              "title": "Ereditarietà"
            }
          },
          {
            "id": "f1c08d6ea964cb8a",
            "type": "leaf",
            "state": {
              "type": "markdown",
              "state": {
                "file": "Ereditarietà Multipla.md",
                "mode": "preview",
                "backlinks": true,
                "source": false
              },
              "icon": "lucide-file",
              "title": "Ereditarietà Multipla"
            }
          }
        ],
        "currentTab": 2
      }
    ],
    "direction": "vertical"
  },
  "left": {
    "id": "41ff92f1d7ace9b2",
    "type": "split",
    "children": [
      {
        "id": "405c7aa571cbe416",
        "type": "tabs",
        "children": [
          {
            "id": "140b31c651f4bd7b",
            "type": "leaf",
            "state": {
              "type": "file-explorer",
              "state": {
                "sortOrder": "alphabetical"
              },
              "icon": "lucide-folder-closed",
              "title": "Files"
            }
          },
          {
            "id": "1945ef0b14746c95",
            "type": "leaf",
            "state": {
              "type": "search",
              "state": {
                "query": "",
                "matchingCase": false,
                "explainSearch": false,
                "collapseAll": false,
                "extraContext": false,
                "sortOrder": "alphabetical"
              },
              "icon": "lucide-search",
              "title": "Search"
            }
          },
          {
            "id": "c7dbc94c366c16c6",
            "type": "leaf",
            "state": {
              "type": "bookmarks",
              "state": {},
              "icon": "lucide-bookmark",
              "title": "Bookmarks"
            }
          }
        ]
      }
    ],
    "direction": "horizontal",
    "width": 200
  },
  "right": {
    "id": "53e7b442ff53f276",
    "type": "split",
    "children": [
      {
        "id": "8fd1538800c729c4",
        "type": "tabs",
        "children": [
          {
            "id": "bb8e870e1ac747e2",
            "type": "leaf",
            "state": {
              "type": "backlink",
              "state": {
                "file": "Benvenuto.md",
                "collapseAll": false,
                "extraContext": false,
                "sortOrder": "alphabetical",
                "showSearch": false,
                "searchQuery": "",
                "backlinkCollapsed": false,
                "unlinkedCollapsed": true
              },
              "icon": "links-coming-in",
              "title": "Riferimenti a Benvenuto"
            }
          },
          {
            "id": "01fc7098b704209a",
            "type": "leaf",
            "state": {
              "type": "outgoing-link",
              "state": {
                "file": "Classi.md",
                "linksCollapsed": false,
                "unlinkedCollapsed": true
              },
              "icon": "links-going-out",
              "title": "Outgoing links from Classi"
            }
          },
          {
            "id": "31148549201666e2",
            "type": "leaf",
            "state": {
              "type": "tag",
              "state": {
                "sortOrder": "frequency",
                "useHierarchy": true
              },
              "icon": "lucide-tags",
              "title": "Tags"
            }
          },
          {
            "id": "20ac371123cac2a2",
            "type": "leaf",
            "state": {
              "type": "outline",
              "state": {
                "file": "Classi.md"
              },
              "icon": "lucide-list",
              "title": "Outline of Classi"
            }
          },
          {
            "id": "8bcea40682e09863",
            "type": "leaf",
            "state": {
              "type": "git-view",
              "state": {},
              "icon": "git-pull-request",
              "title": "Source Control"
            }
          }
        ],
        "currentTab": 4
      }
    ],
    "direction": "horizontal",
    "width": 300
  },
  "left-ribbon": {
    "hiddenItems": {
      "switcher:Open quick switcher": false,
      "graph:Open graph view": false,
      "canvas:Create new canvas": false,
      "daily-notes:Open today's daily note": false,
      "templates:Insert template": false,
      "command-palette:Open command palette": false,
      "markdown-importer:Open format converter": false,
      "obsidian-git:Open Git source control": false,
      "obsidian-excalidraw-plugin:Create new drawing": false
    }
  },
  "active": "f1c08d6ea964cb8a",
  "lastOpenFiles": [
    "Ereditarietà.md",
    "Ereditarietà Multipla.md",
    "Eccezioni.md",
    "Excalidraw/Drawing 2024-12-02 10.35.50.excalidraw.md",
    "Excalidraw",
    "Canvas/Drawing 2024-12-02 10.22.30.excalidraw.md",
    "Canvas/Vtable_C.canvas",
    "Classi.md",
    "Canvas",
    "Costruttori.md",
    "Template.md",
    "Copie, Assegnazione, Distruzioni Profonde.md",
    "Overload Di Operatori.md",
    "Untitled 1.md",
    "Problema dell'interferenza.md",
    "Programmazione.md",
    "22-11-2024.md",
    "Dichiarazioni Incomplete.md",
    "References.md",
    "Dichiarazioni Incom.md",
    "Distruttore.md",
    "Copie,.md",
    "Distruzione Profonda.md",
    "Iteratori.md",
    "Friend.md",
    "Cast.md",
    "21-11-2024.md",
    "Namespace.md",
    "Classi Annidate.md",
    "Untitled.canvas",
    "Canvas/PAO_C.canvas",
    "Canvas",
    "Tags"
  ]
}